Workbook

Sheet Dashboard
A1: 🏦 PERSONAL FINANCE MASTER SYSTEM | Dashboard
A2: Your Personal Financial Operating System
A4: 💸 Total Expenses | C4: 🏦 Total Savings | E4: 📈 Investment Value | G4: 💰 Net Worth | I4: 📊 Savings Rate | K4: 🗓️ Months Tracked
A5: =IFERROR(Expenses!G15,0) -> 0 | C5: =IFERROR(SUM(Savings!C3:C1000),0) -> 0 | E5: =IFERROR(Investments!G8,0) -> 0 | G5: =IFERROR('Net Worth'!A22,0) -> 0 | I5: =IFERROR('Monthly Summary'!F8,0) -> 0 | K5: =COUNTA('Monthly Summary'!A3:A1000) -> 6
A7: 📊 Category Breakdown — Current Month | H7: 📅 Monthly Spending Trend
A8: Expense Categories | H8: Monthly Snapshot
A9: Food | D9: =IFERROR(SUMIF(Expenses!C:C,"Food",Expenses!G:G),0) -> 0 | H9: Latest Month Income | K9: =IFERROR('Monthly Summary'!B8,0) -> 0
A10: Transport | D10: =IFERROR(SUMIF(Expenses!C:C,"Transport",Expenses!G:G),0) -> 0 | H10: Latest Month Expenses | K10: =IFERROR('Monthly Summary'!C8,0) -> 0
A11: Shopping | D11: =IFERROR(SUMIF(Expenses!C:C,"Shopping",Expenses!G:G),0) -> 0 | H11: Latest Month Savings | K11: =IFERROR('Monthly Summary'!D8,0) -> 0
A12: Entertainment | D12: =IFERROR(SUMIF(Expenses!C:C,"Entertainment",Expenses!G:G),0) -> 0 | H12: Latest Savings Rate | K12: =IFERROR('Monthly Summary'!F8,0) -> 0
A13: Education | D13: =IFERROR(SUMIF(Expenses!C:C,"Education",Expenses!G:G),0) -> 0 | H13: Avg Monthly Expenses | K13: =IFERROR(AVERAGE('Monthly Summary'!C3:C100),0) -> 0
A14: Health | D14: =IFERROR(SUMIF(Expenses!C:C,"Health",Expenses!G:G),0) -> 0 | H14: Total Invested | K14: =IFERROR(SUM('Monthly Summary'!E3:E100),0) -> 0
A15: Bills | D15: =IFERROR(SUMIF(Expenses!C:C,"Bills",Expenses!G:G),0) -> 0
A16: Subscriptions | D16: =IFERROR(SUMIF(Expenses!C:C,"Subscriptions",Expenses!G:G),0) -> 0
A17: Miscellaneous | D17: =IFERROR(SUMIF(Expenses!C:C,"Miscellaneous",Expenses!G:G),0) -> 0
A19: 💡 HOW TO USE: Enter data in Expenses → Savings → Investments → Monthly Summary sheets. This Dashboard updates automatically.
M21: Food | N21: =IFERROR(SUMIF(Expenses!C:C,M21,Expenses!G:G),0) -> 0
M22: Transport | N22: =IFERROR(SUMIF(Expenses!C:C,M22,Expenses!G:G),0) -> 0
M23: Shopping | N23: =IFERROR(SUMIF(Expenses!C:C,M23,Expenses!G:G),0) -> 0
M24: Entertainment | N24: =IFERROR(SUMIF(Expenses!C:C,M24,Expenses!G:G),0) -> 0
M25: Education | N25: =IFERROR(SUMIF(Expenses!C:C,M25,Expenses!G:G),0) -> 0
M26: Health | N26: =IFERROR(SUMIF(Expenses!C:C,M26,Expenses!G:G),0) -> 0
M27: Bills | N27: =IFERROR(SUMIF(Expenses!C:C,M27,Expenses!G:G),0) -> 0
M28: Subscriptions | N28: =IFERROR(SUMIF(Expenses!C:C,M28,Expenses!G:G),0) -> 0
M29: Miscellaneous | N29: =IFERROR(SUMIF(Expenses!C:C,M29,Expenses!G:G),0) -> 0

Sheet Expenses
A1: 💸 Expense Tracker
A2: Date | B2: Month | C2: Category | D2: Description | E2: Payment Method | F2: Need/Want | G2: Amount (₹)
A14: 📊 Expense Summary
A15: Total Spending | G15: =SUM(G3:G13) -> 0
A16: Total Needs | G16: =SUMIF(F3:F1000,"Need",G3:G1000) -> 0
A17: Total Wants | G17: =SUMIF(F3:F1000,"Want",G3:G1000) -> 0
A18: Highest Expense | G18: =IFERROR(MAX(G3:G1000),0) -> 0
A19: No. of Transactions | G19: =COUNTA(A3:A1000) -> 6

Sheet Savings
A1: 🏦 Savings Tracker
A2: Savings Goal | B2: Target Amount (₹) | C2: Current Saved (₹) | D2: Remaining (₹) | E2: Deadline | F2: Progress %
A3: Emergency Fund | E3: Dec-2026 | F3: =IFERROR(C3/B3,0) -> 0
A4: Laptop | E4: Dec-2026 | F4: =IFERROR(C4/B4,0) -> 0
A5: Vacation | E5: Dec-2026 | F5: =IFERROR(C5/B5,0) -> 0
A6: Investment Capital | E6: Dec-2026 | F6: =IFERROR(C6/B6,0) -> 0
A7: Car Down Payment | E7: Dec-2026 | F7: =IFERROR(C7/B7,0) -> 0

Sheet Investments
A1: 📈 Investment Portfolio
A2: Asset | B2: Type | C2: Qty | D2: Buy Price (₹) | E2: Current Price (₹) | F2: Invested Value (₹) | G2: Current Value (₹) | H2: Profit/Loss (₹) | I2: ROI %
G3: =C3*E3 -> 0 | H3: =G3-F3 -> 0 | I3: =IFERROR(H3/F3,0) -> 0
G4: =C4*E4 -> 0 | H4: =G4-F4 -> 0 | I4: =IFERROR(H4/F4,0) -> 0
G5: =C5*E5 -> 0 | H5: =G5-F5 -> 0 | I5: =IFERROR(H5/F5,0) -> 0
G6: =C6*E6 -> 0 | H6: =G6-F6 -> 0 | I6: =IFERROR(H6/F6,0) -> 0
G7: =C7*E7 -> 0 | H7: =G7-F7 -> 0 | I7: =IFERROR(H7/F7,0) -> 0
A8: TOTAL | F8: =SUM(F3:F7) -> 0 | G8: =SUM(G3:G7) -> 0 | H8: =SUM(H3:H7) -> 0 | I8: =IFERROR(H8/F8,0) -> 0

Sheet Monthly Summary
A1: 📅 Monthly Financial Summary
A2: Month | B2: Income (₹) | C2: Expenses (₹) | D2: Savings (₹) | E2: Investments (₹) | F2: Savings Rate
A3: January | D3: =B3-C3 -> 0 | F3: =IFERROR(D3/B3,0) -> 0
A4: February | D4: =B4-C4 -> 0 | F4: =IFERROR(D4/B4,0) -> 0
A5: March | D5: =B5-C5 -> 0 | F5: =IFERROR(D5/B5,0) -> 0
A6: April | D6: =B6-C6 -> 0 | F6: =IFERROR(D6/B6,0) -> 0
A7: May | D7: =B7-C7 -> 0 | F7: =IFERROR(D7/B7,0) -> 0
A8: June | D8: =B8-C8 -> 0 | F8: =IFERROR(D8/B8,0) -> 0

Sheet Net Worth
A1: 💰 Net Worth Tracker
A3: ASSETS | B3: Value (₹)
A4: Cash & Bank Balance
A5: Savings Accounts
A6: Investments | B6: 0
A7: Gold / Jewellery
A8: Other Assets
A9: Investment Portfolio Value | B9: =IFERROR(Investments!G8,0) -> 0
A10: TOTAL ASSETS | B10: =SUM(B4:B9) -> 0
A12: LIABILITIES | B12: Value (₹)
A13: Personal Loans | B13: 0
A14: Home Loan | B14: 0
A15: Car Loan | B15: 0
A16: Credit Card Outstanding | B16: 0
A17: Other Liabilities | B17: 0
A18: TOTAL LIABILITIES | B18: =SUM(B13:B17) -> 0
A20: NET WORTH = Assets − Liabilities
A21: =B10-B18 -> 0

Sheet Goals
A1: 🎯 Financial Goals
A2: Goal | B2: Target Amount (₹) | C2: Saved So Far (₹) | D2: Deadline | E2: Monthly Required (₹)
A3: Laptop | D3: Dec-2026 | E3: =IFERROR((B3-C3)/12,0) -> 0
A4: Emergency Fund | D4: Jun-2027 | E4: =IFERROR((B4-C4)/12,0) -> 0
A5: Investment Capital | D5: Jan-2027 | E5: =IFERROR((B5-C5)/12,0) -> 0
A6: Vacation Fund | D6: Mar-2026 | E6: =IFERROR((B6-C6)/12,0) -> 0
A7: Car Down Payment | D7: Dec-2028 | E7: =IFERROR((B7-C7)/12,0) -> 0

Sheet SIP Calculator
A1: 📊 SIP & Compound Growth Calculator
A3: INPUTS | B3: Value
A4: Monthly SIP Amount (₹)
A5: Expected Annual Return (%)
A6: Investment Duration (Years)
A8: RESULTS | B8: Calculated Value
A9: Total Amount Invested (₹) | B9: =B4*B6*12 -> 0
A10: Future Value (₹) | B10: =IFERROR(FV(B5/100/12,B6*12,-B4),0) -> 0
A11: Total Returns / Wealth Gain (₹) | B11: =IFERROR(B10-B9,0) -> 0
A12: Return Multiple | B12: =IFERROR(B10/B9,0) -> 0

Sheet Emergency Fund
A1: 🛡️ Emergency Fund Planner
A2: Monthly Expenses (₹) | B2: Target Months | C2: Required Fund (₹) | D2: Currently Saved (₹) | E2: Remaining (₹)
C3: =A3*B3 -> 0 | E3: =IFERROR(C3-D3,0) -> 0
A5: 💡 Why You Need an Emergency Fund
A6: ✅ Covers 3–6 months of living expenses
A7: ✅ Protects investments — no panic selling needed
A8: ✅ Provides financial safety net for job loss or medical emergencies
A9: ✅ Keep in a liquid instrument: savings account or liquid mutual fund
A10: ✅ Do NOT invest your emergency fund in stocks

Sheet Categories
A1: Master Category Lists
A3: Expense Categories | B3: Payment Methods | C3: Need / Want
A4: Food | B4: Cash | C4: Need
A5: Transport | B5: UPI | C5: Want
A6: Shopping | B6: Card
A7: Entertainment | B7: Bank Transfer
A8: Education
A9: Health
A10: Bills
A11: Subscriptions
A12: Family
A13: Miscellaneous
